tba_pydata/__init__.py
tba_pydata/analysis.py
tba_pydata/api.py
tba_pydata/constants.py
tba_pydata/games/__init__.py
tba_pydata/games/power_up_2018.py
tba_pydata-0.1.1.dist-info/METADATA
tba_pydata-0.1.1.dist-info/RECORD
tba_pydata-0.1.1.dist-info/WHEEL
tba_pydata-0.1.1.dist-info/top_level.txt
