Metadata-Version: 2.1
Name: tba-pydata
Version: 0.1.1
Summary: Wrapper for working with the Blue Alliance API in pandas
Home-page: https://github.com/Thing342/TBA-PyData
Author: Wes Jordan
Author-email: wes@wesj.org
License: MIT
Keywords: thebluealliance,frc,pydata,tba
Platform: UNKNOWN
Classifier: License :: OSI Approved :: MIT License
Classifier: Programming Language :: Python :: 3.5
Classifier: Programming Language :: Python :: 3.6
Classifier: Programming Language :: Python :: 3.7
Requires-Dist: numpy
Requires-Dist: requests
Requires-Dist: pandas
Requires-Dist: statsmodels
